flask_constance/__init__.py
flask_constance/admin/__init__.py
flask_constance/admin/form.py
flask_constance/admin/templates/settings.html.j2
flask_constance/admin/view.py
flask_constance/backends/__init__.py
flask_constance/backends/base.py
flask_constance/backends/fsqla.py
flask_constance/backends/memory.py
flask_constance/cli.py
flask_constance/core.py
flask_constance/globals.py
flask_constance/py.typed
flask_constance/signals.py
flask_constance/storage.py
flask_constance/view.py
flask_constance-0.1.2.dist-info/LICENSE
flask_constance-0.1.2.dist-info/METADATA
flask_constance-0.1.2.dist-info/WHEEL
flask_constance-0.1.2.dist-info/RECORD
